nornir_utils/__init__.py
nornir_utils/plugins/__init__.py
nornir_utils/plugins/functions/__init__.py
nornir_utils/plugins/functions/print_result.py
nornir_utils/plugins/inventory/__init__.py
nornir_utils/plugins/inventory/yaml_inventory.py
nornir_utils/plugins/processors/__init__.py
nornir_utils/plugins/processors/print_result.py
nornir_utils/plugins/tasks/__init__.py
nornir_utils/plugins/tasks/data/__init__.py
nornir_utils/plugins/tasks/data/echo_data.py
nornir_utils/plugins/tasks/data/load_json.py
nornir_utils/plugins/tasks/data/load_yaml.py
nornir_utils-0.1.0a1.dist-info/entry_points.txt
nornir_utils-0.1.0a1.dist-info/LICENSE
nornir_utils-0.1.0a1.dist-info/WHEEL
nornir_utils-0.1.0a1.dist-info/METADATA
nornir_utils-0.1.0a1.dist-info/RECORD
